elfen/__init__.py
elfen/custom.py
elfen/dependency.py
elfen/emotion.py
elfen/entities.py
elfen/extractor.py
elfen/features.py
elfen/generic.py
elfen/information.py
elfen/lexical_richness.py
elfen/morphological.py
elfen/pos.py
elfen/preprocess.py
elfen/psycholinguistic.py
elfen/ratios.py
elfen/readability.py
elfen/resources.py
elfen/schemas.py
elfen/semantic.py
elfen/surface.py
elfen/util.py
elfen/configs/__init__.py
elfen/configs/dependency_config.py
elfen/configs/extractor_config.py
elfen/configs/morphological_config.py
elfen/resource_utils/langs.py
elfen/resource_utils/psycholinguistics.py
elfen/resource_utils/resource_map.py
elfen-1.2.8.dist-info/licenses/LICENSE
elfen-1.2.8.dist-info/METADATA
elfen-1.2.8.dist-info/WHEEL
elfen-1.2.8.dist-info/top_level.txt
elfen-1.2.8.dist-info/RECORD
