Metadata-Version: 2.4
Name: elfen
Version: 1.2.8
Summary: ELFEN - Efficient Linguistic Feature Extraction for Natural Language Datasets
Author-email: Maximilian Maurer <mmmaurer@pm.me>
Project-URL: Homepage, https://github.com/mmmaurer/elfen
Project-URL: Issues, https://github.com/mmmaurer/elfen/issues
Classifier: Programming Language :: Python :: 3.10
Classifier: Programming Language :: Python :: 3.11
Classifier: Programming Language :: Python :: 3.12
Classifier: License :: OSI Approved :: MIT License
Classifier: Operating System :: OS Independent
Requires-Python: <=3.12.11,>=3.10
License-File: LICENSE
Requires-Dist: polars>=1.10.0
Requires-Dist: numpy>=1.26.4
Requires-Dist: scipy>=1.14.1
Requires-Dist: spacy>=3.7.5
Requires-Dist: spacy_syllables>=3.0.2
Requires-Dist: stanza>=1.8.2
Requires-Dist: Requests>=2.32.3
Requires-Dist: wn>=0.9.5
Requires-Dist: fastexcel>=0.12.0
Requires-Dist: spacy-transformers>=1.3.5
Requires-Dist: pyarrow>=19.0.0
Dynamic: license-file
